{
  "hotels": [
    {
      "name": "Victoria",
      "amountRoom": "3",
      "available": "2",
      "rooms": [
        {
          "number": "1",
          "subscribe": "Одиночная комната, 15м.кв., двойная кровать, душевая, туалет",
          "price": "400 грн",
          "available": "false"
        },
        {
          "number": "2",
          "subscribe": "Две комнаты, 20м.кв. и 12м.кв., двойная кровать + одинарная, ванная, туалет ",
          "price": "700 грн",
          "available": "true"
        },
        {
          "number": "3",
          "subscribe": "VIP. Три комнаты: две спальные по 20м.кв., одна - гостевая 30м.кв; две двухспальные кровати, душевая, ванная, два туалета",
          "price": "1000 грн",
          "available": "true"
        }
      ]
    },
    {
      "name": "Сальвадор Дали",
      "amountRoom": "2",
      "available": "1",
      "rooms": [
        {
          "number": "1",
          "subscribe": "VIP-family. Три комнаты: две спальные по 25м.кв., одна - гостевая 30м.кв; две двухспальные кровати, душевая, ванная, два туалета",
          "price": "1200 грн",
          "available": "true"
        },
        {
          "number": "2",
          "subscribe": "VIP. Три комнаты: две спальные по 25м.кв., одна - гостевая 25м.кв; две двухспальные кровати, две ванные комнаты, в каждой - ванная, би-де, туалет отдельно",
          "price": "1200 грн",
          "available": "false"
        }
      ]
    }
  ]
}
